aiocian/__init__.py
aiocian/client.py
aiocian/constants.py
aiocian/exceptions.py
aiocian-0.0.3.dist-info/LICENSE
aiocian-0.0.3.dist-info/METADATA
aiocian-0.0.3.dist-info/WHEEL
aiocian-0.0.3.dist-info/top_level.txt
aiocian-0.0.3.dist-info/RECORD
