Metadata-Version: 2.1
Name: aiocian
Version: 0.0.3
Summary: UNKNOWN
Home-page: https://github.com/OlegYurchik/aiocian
Author: Oleg Yurchik
Author-email: oleg.yurchik@protonmail.com
License: UNKNOWN
Platform: UNKNOWN
Requires-Python: >=3.6
Requires-Dist: aiohttp
Requires-Dist: requests
